{
  "version": 1,
  "org": "developer-arman",
  "repo": "aemdemo",
  "contentSource": {
    "url": "https://content.da.live/developer-arman/aemdemo/",
    "type": "onedrive"
  },
  "code": {
    "owner": "developer-arman",
    "repo": "aemdemo",
    "source": {
      "type": "github",
      "url": "https://github.com/developer-arman/aemdemo"
    }
  },
  "cdn": {
    "live": {
      "host": "main--aemdemo--developer-arman.aem.live"
    },
    "preview": {
      "host": "main--aemdemo--developer-arman.aem.page"
    }
  },
  "plugins": [
    {
      "id": "library",
      "title": "Block Library",
      "environments": ["edit"],
      "url": "/block-library.json",
      "isPalette": true
    }
  ]
}